[
  {
    "id": "23010401",
    "level": 4,
    "level_name": {
      "th": "หมู่บ้าน",
      "en": "village"
    },
    "name": {
      "th": "บ้านแหลมหิน",
      "en": "Ban Laem Hin",
      "slug": "23010401"
    },
    "code": {
      "dopa": "23010401"
    },
    "parent": {
      "id": "230104",
      "level": 3,
      "name": {
        "th": "หนองคันทรง",
        "en": "Nong Khan Song",
        "slug": "nong-khan-song"
      }
    },
    "ancestors": [
      {
        "id": "23",
        "level": 1,
        "name": {
          "th": "ตราด",
          "en": "Trat",
          "slug": "trat"
        }
      },
      {
        "id": "2301",
        "level": 2,
        "name": {
          "th": "เมืองตราด",
          "en": "Mueang Trat",
          "slug": "mueang-trat"
        }
      },
      {
        "id": "230104",
        "level": 3,
        "name": {
          "th": "หนองคันทรง",
          "en": "Nong Khan Song",
          "slug": "nong-khan-song"
        }
      }
    ],
    "children_count": {},
    "metadata": {},
    "geo": {
      "lat": "12.180526",
      "lon": "102.559634"
    },
    "source": {}
  },
  {
    "id": "23010402",
    "level": 4,
    "level_name": {
      "th": "หมู่บ้าน",
      "en": "village"
    },
    "name": {
      "th": "บ้านท่าระแนะ",
      "en": "Ban Tha Ra Nae",
      "slug": "23010402"
    },
    "code": {
      "dopa": "23010402"
    },
    "parent": {
      "id": "230104",
      "level": 3,
      "name": {
        "th": "หนองคันทรง",
        "en": "Nong Khan Song",
        "slug": "nong-khan-song"
      }
    },
    "ancestors": [
      {
        "id": "23",
        "level": 1,
        "name": {
          "th": "ตราด",
          "en": "Trat",
          "slug": "trat"
        }
      },
      {
        "id": "2301",
        "level": 2,
        "name": {
          "th": "เมืองตราด",
          "en": "Mueang Trat",
          "slug": "mueang-trat"
        }
      },
      {
        "id": "230104",
        "level": 3,
        "name": {
          "th": "หนองคันทรง",
          "en": "Nong Khan Song",
          "slug": "nong-khan-song"
        }
      }
    ],
    "children_count": {},
    "metadata": {},
    "geo": {
      "lat": "12.1794130",
      "lon": "102.5428814"
    },
    "source": {}
  },
  {
    "id": "23010403",
    "level": 4,
    "level_name": {
      "th": "หมู่บ้าน",
      "en": "village"
    },
    "name": {
      "th": "บ้านหนองคันทรง",
      "en": "Ban Nong Khan Song",
      "slug": "23010403"
    },
    "code": {
      "dopa": "23010403"
    },
    "parent": {
      "id": "230104",
      "level": 3,
      "name": {
        "th": "หนองคันทรง",
        "en": "Nong Khan Song",
        "slug": "nong-khan-song"
      }
    },
    "ancestors": [
      {
        "id": "23",
        "level": 1,
        "name": {
          "th": "ตราด",
          "en": "Trat",
          "slug": "trat"
        }
      },
      {
        "id": "2301",
        "level": 2,
        "name": {
          "th": "เมืองตราด",
          "en": "Mueang Trat",
          "slug": "mueang-trat"
        }
      },
      {
        "id": "230104",
        "level": 3,
        "name": {
          "th": "หนองคันทรง",
          "en": "Nong Khan Song",
          "slug": "nong-khan-song"
        }
      }
    ],
    "children_count": {},
    "metadata": {},
    "geo": {
      "lat": "12.187983",
      "lon": "102.540615"
    },
    "source": {}
  },
  {
    "id": "23010404",
    "level": 4,
    "level_name": {
      "th": "หมู่บ้าน",
      "en": "village"
    },
    "name": {
      "th": "บ้านหนองคันทรง",
      "en": "Ban Nong Khan Song",
      "slug": "23010404"
    },
    "code": {
      "dopa": "23010404"
    },
    "parent": {
      "id": "230104",
      "level": 3,
      "name": {
        "th": "หนองคันทรง",
        "en": "Nong Khan Song",
        "slug": "nong-khan-song"
      }
    },
    "ancestors": [
      {
        "id": "23",
        "level": 1,
        "name": {
          "th": "ตราด",
          "en": "Trat",
          "slug": "trat"
        }
      },
      {
        "id": "2301",
        "level": 2,
        "name": {
          "th": "เมืองตราด",
          "en": "Mueang Trat",
          "slug": "mueang-trat"
        }
      },
      {
        "id": "230104",
        "level": 3,
        "name": {
          "th": "หนองคันทรง",
          "en": "Nong Khan Song",
          "slug": "nong-khan-song"
        }
      }
    ],
    "children_count": {},
    "metadata": {},
    "geo": {
      "lat": "12.201823810387802",
      "lon": "102.52145424485207"
    },
    "source": {}
  },
  {
    "id": "23010405",
    "level": 4,
    "level_name": {
      "th": "หมู่บ้าน",
      "en": "village"
    },
    "name": {
      "th": "บ้านแหลมสำโรง",
      "en": "Ban Laem Samrong",
      "slug": "23010405"
    },
    "code": {
      "dopa": "23010405"
    },
    "parent": {
      "id": "230104",
      "level": 3,
      "name": {
        "th": "หนองคันทรง",
        "en": "Nong Khan Song",
        "slug": "nong-khan-song"
      }
    },
    "ancestors": [
      {
        "id": "23",
        "level": 1,
        "name": {
          "th": "ตราด",
          "en": "Trat",
          "slug": "trat"
        }
      },
      {
        "id": "2301",
        "level": 2,
        "name": {
          "th": "เมืองตราด",
          "en": "Mueang Trat",
          "slug": "mueang-trat"
        }
      },
      {
        "id": "230104",
        "level": 3,
        "name": {
          "th": "หนองคันทรง",
          "en": "Nong Khan Song",
          "slug": "nong-khan-song"
        }
      }
    ],
    "children_count": {},
    "metadata": {},
    "geo": {
      "lat": "12.201325",
      "lon": "102.523576"
    },
    "source": {}
  }
]