[
  {
    "id": "65090501",
    "level": 4,
    "level_name": {
      "th": "หมู่บ้าน",
      "en": "village"
    },
    "name": {
      "th": "บ้านหนองไม้ยางดำ",
      "en": "Ban Nong Mai Yang Dam",
      "slug": "65090501"
    },
    "code": {
      "dopa": "65090501"
    },
    "parent": {
      "id": "650905",
      "level": 3,
      "name": {
        "th": "บ้านน้อยซุ้มขี้เหล็ก",
        "en": "Ban Noi Sum Khilek",
        "slug": "ban-noi-sum-khilek"
      }
    },
    "ancestors": [
      {
        "id": "65",
        "level": 1,
        "name": {
          "th": "พิษณุโลก",
          "en": "Phitsanulok",
          "slug": "phitsanulok"
        }
      },
      {
        "id": "6509",
        "level": 2,
        "name": {
          "th": "เนินมะปราง",
          "en": "Noen Maprang",
          "slug": "noen-maprang"
        }
      },
      {
        "id": "650905",
        "level": 3,
        "name": {
          "th": "บ้านน้อยซุ้มขี้เหล็ก",
          "en": "Ban Noi Sum Khilek",
          "slug": "ban-noi-sum-khilek"
        }
      }
    ],
    "children_count": {},
    "metadata": {},
    "geo": {
      "lat": "16.488026796310564",
      "lon": "100.6079663336277"
    },
    "source": {}
  },
  {
    "id": "65090502",
    "level": 4,
    "level_name": {
      "th": "หมู่บ้าน",
      "en": "village"
    },
    "name": {
      "th": "บ้านน้อย",
      "en": "Ban Noi",
      "slug": "65090502"
    },
    "code": {
      "dopa": "65090502"
    },
    "parent": {
      "id": "650905",
      "level": 3,
      "name": {
        "th": "บ้านน้อยซุ้มขี้เหล็ก",
        "en": "Ban Noi Sum Khilek",
        "slug": "ban-noi-sum-khilek"
      }
    },
    "ancestors": [
      {
        "id": "65",
        "level": 1,
        "name": {
          "th": "พิษณุโลก",
          "en": "Phitsanulok",
          "slug": "phitsanulok"
        }
      },
      {
        "id": "6509",
        "level": 2,
        "name": {
          "th": "เนินมะปราง",
          "en": "Noen Maprang",
          "slug": "noen-maprang"
        }
      },
      {
        "id": "650905",
        "level": 3,
        "name": {
          "th": "บ้านน้อยซุ้มขี้เหล็ก",
          "en": "Ban Noi Sum Khilek",
          "slug": "ban-noi-sum-khilek"
        }
      }
    ],
    "children_count": {},
    "metadata": {},
    "geo": {
      "lat": "16.523397668279422",
      "lon": "100.60098990797997"
    },
    "source": {}
  },
  {
    "id": "65090503",
    "level": 4,
    "level_name": {
      "th": "หมู่บ้าน",
      "en": "village"
    },
    "name": {
      "th": "บ้านโปร่งไผ่",
      "en": "Ban Prong Phai",
      "slug": "65090503"
    },
    "code": {
      "dopa": "65090503"
    },
    "parent": {
      "id": "650905",
      "level": 3,
      "name": {
        "th": "บ้านน้อยซุ้มขี้เหล็ก",
        "en": "Ban Noi Sum Khilek",
        "slug": "ban-noi-sum-khilek"
      }
    },
    "ancestors": [
      {
        "id": "65",
        "level": 1,
        "name": {
          "th": "พิษณุโลก",
          "en": "Phitsanulok",
          "slug": "phitsanulok"
        }
      },
      {
        "id": "6509",
        "level": 2,
        "name": {
          "th": "เนินมะปราง",
          "en": "Noen Maprang",
          "slug": "noen-maprang"
        }
      },
      {
        "id": "650905",
        "level": 3,
        "name": {
          "th": "บ้านน้อยซุ้มขี้เหล็ก",
          "en": "Ban Noi Sum Khilek",
          "slug": "ban-noi-sum-khilek"
        }
      }
    ],
    "children_count": {},
    "metadata": {},
    "geo": {
      "lat": "16.535411079205836",
      "lon": "100.60205608606339"
    },
    "source": {}
  },
  {
    "id": "65090504",
    "level": 4,
    "level_name": {
      "th": "หมู่บ้าน",
      "en": "village"
    },
    "name": {
      "th": "บ้านซุ้มขี้เหล็ก",
      "en": "Ban Sum Khilek",
      "slug": "65090504"
    },
    "code": {
      "dopa": "65090504"
    },
    "parent": {
      "id": "650905",
      "level": 3,
      "name": {
        "th": "บ้านน้อยซุ้มขี้เหล็ก",
        "en": "Ban Noi Sum Khilek",
        "slug": "ban-noi-sum-khilek"
      }
    },
    "ancestors": [
      {
        "id": "65",
        "level": 1,
        "name": {
          "th": "พิษณุโลก",
          "en": "Phitsanulok",
          "slug": "phitsanulok"
        }
      },
      {
        "id": "6509",
        "level": 2,
        "name": {
          "th": "เนินมะปราง",
          "en": "Noen Maprang",
          "slug": "noen-maprang"
        }
      },
      {
        "id": "650905",
        "level": 3,
        "name": {
          "th": "บ้านน้อยซุ้มขี้เหล็ก",
          "en": "Ban Noi Sum Khilek",
          "slug": "ban-noi-sum-khilek"
        }
      }
    ],
    "children_count": {},
    "metadata": {},
    "geo": {
      "lat": "16.56237553136451",
      "lon": "100.6133508682251"
    },
    "source": {}
  },
  {
    "id": "65090505",
    "level": 4,
    "level_name": {
      "th": "หมู่บ้าน",
      "en": "village"
    },
    "name": {
      "th": "บ้านพัฒนาดงน้อย",
      "en": "Ban Phatthana Dong Noi",
      "slug": "65090505"
    },
    "code": {
      "dopa": "65090505"
    },
    "parent": {
      "id": "650905",
      "level": 3,
      "name": {
        "th": "บ้านน้อยซุ้มขี้เหล็ก",
        "en": "Ban Noi Sum Khilek",
        "slug": "ban-noi-sum-khilek"
      }
    },
    "ancestors": [
      {
        "id": "65",
        "level": 1,
        "name": {
          "th": "พิษณุโลก",
          "en": "Phitsanulok",
          "slug": "phitsanulok"
        }
      },
      {
        "id": "6509",
        "level": 2,
        "name": {
          "th": "เนินมะปราง",
          "en": "Noen Maprang",
          "slug": "noen-maprang"
        }
      },
      {
        "id": "650905",
        "level": 3,
        "name": {
          "th": "บ้านน้อยซุ้มขี้เหล็ก",
          "en": "Ban Noi Sum Khilek",
          "slug": "ban-noi-sum-khilek"
        }
      }
    ],
    "children_count": {},
    "metadata": {},
    "geo": {
      "lat": "16.56251693213731",
      "lon": "100.6125220656395"
    },
    "source": {}
  },
  {
    "id": "65090506",
    "level": 4,
    "level_name": {
      "th": "หมู่บ้าน",
      "en": "village"
    },
    "name": {
      "th": "บ้านคลองปากน้ำ",
      "en": "Ban Khlong Pak Nam",
      "slug": "65090506"
    },
    "code": {
      "dopa": "65090506"
    },
    "parent": {
      "id": "650905",
      "level": 3,
      "name": {
        "th": "บ้านน้อยซุ้มขี้เหล็ก",
        "en": "Ban Noi Sum Khilek",
        "slug": "ban-noi-sum-khilek"
      }
    },
    "ancestors": [
      {
        "id": "65",
        "level": 1,
        "name": {
          "th": "พิษณุโลก",
          "en": "Phitsanulok",
          "slug": "phitsanulok"
        }
      },
      {
        "id": "6509",
        "level": 2,
        "name": {
          "th": "เนินมะปราง",
          "en": "Noen Maprang",
          "slug": "noen-maprang"
        }
      },
      {
        "id": "650905",
        "level": 3,
        "name": {
          "th": "บ้านน้อยซุ้มขี้เหล็ก",
          "en": "Ban Noi Sum Khilek",
          "slug": "ban-noi-sum-khilek"
        }
      }
    ],
    "children_count": {},
    "metadata": {},
    "geo": {
      "lat": "16.51005655807866",
      "lon": "100.63957214355469"
    },
    "source": {}
  },
  {
    "id": "65090507",
    "level": 4,
    "level_name": {
      "th": "หมู่บ้าน",
      "en": "village"
    },
    "name": {
      "th": "บ้านคลองไร่",
      "en": "Ban Khlong Rai",
      "slug": "65090507"
    },
    "code": {
      "dopa": "65090507"
    },
    "parent": {
      "id": "650905",
      "level": 3,
      "name": {
        "th": "บ้านน้อยซุ้มขี้เหล็ก",
        "en": "Ban Noi Sum Khilek",
        "slug": "ban-noi-sum-khilek"
      }
    },
    "ancestors": [
      {
        "id": "65",
        "level": 1,
        "name": {
          "th": "พิษณุโลก",
          "en": "Phitsanulok",
          "slug": "phitsanulok"
        }
      },
      {
        "id": "6509",
        "level": 2,
        "name": {
          "th": "เนินมะปราง",
          "en": "Noen Maprang",
          "slug": "noen-maprang"
        }
      },
      {
        "id": "650905",
        "level": 3,
        "name": {
          "th": "บ้านน้อยซุ้มขี้เหล็ก",
          "en": "Ban Noi Sum Khilek",
          "slug": "ban-noi-sum-khilek"
        }
      }
    ],
    "children_count": {},
    "metadata": {},
    "geo": {
      "lat": "16.571562509492985",
      "lon": "100.59953212738037"
    },
    "source": {}
  },
  {
    "id": "65090508",
    "level": 4,
    "level_name": {
      "th": "หมู่บ้าน",
      "en": "village"
    },
    "name": {
      "th": "บ้านคลองแสลงใหม่",
      "en": "Ban Khlong Salaeng Phatthana",
      "slug": "65090508"
    },
    "code": {
      "dopa": "65090508"
    },
    "parent": {
      "id": "650905",
      "level": 3,
      "name": {
        "th": "บ้านน้อยซุ้มขี้เหล็ก",
        "en": "Ban Noi Sum Khilek",
        "slug": "ban-noi-sum-khilek"
      }
    },
    "ancestors": [
      {
        "id": "65",
        "level": 1,
        "name": {
          "th": "พิษณุโลก",
          "en": "Phitsanulok",
          "slug": "phitsanulok"
        }
      },
      {
        "id": "6509",
        "level": 2,
        "name": {
          "th": "เนินมะปราง",
          "en": "Noen Maprang",
          "slug": "noen-maprang"
        }
      },
      {
        "id": "650905",
        "level": 3,
        "name": {
          "th": "บ้านน้อยซุ้มขี้เหล็ก",
          "en": "Ban Noi Sum Khilek",
          "slug": "ban-noi-sum-khilek"
        }
      }
    ],
    "children_count": {},
    "metadata": {},
    "geo": {
      "lat": "16.56237681682655",
      "lon": "100.61334818601608"
    },
    "source": {}
  },
  {
    "id": "65090509",
    "level": 4,
    "level_name": {
      "th": "หมู่บ้าน",
      "en": "village"
    },
    "name": {
      "th": "บ้านใหม่เจริญพร",
      "en": "Ban Mai Charoen Phon",
      "slug": "65090509"
    },
    "code": {
      "dopa": "65090509"
    },
    "parent": {
      "id": "650905",
      "level": 3,
      "name": {
        "th": "บ้านน้อยซุ้มขี้เหล็ก",
        "en": "Ban Noi Sum Khilek",
        "slug": "ban-noi-sum-khilek"
      }
    },
    "ancestors": [
      {
        "id": "65",
        "level": 1,
        "name": {
          "th": "พิษณุโลก",
          "en": "Phitsanulok",
          "slug": "phitsanulok"
        }
      },
      {
        "id": "6509",
        "level": 2,
        "name": {
          "th": "เนินมะปราง",
          "en": "Noen Maprang",
          "slug": "noen-maprang"
        }
      },
      {
        "id": "650905",
        "level": 3,
        "name": {
          "th": "บ้านน้อยซุ้มขี้เหล็ก",
          "en": "Ban Noi Sum Khilek",
          "slug": "ban-noi-sum-khilek"
        }
      }
    ],
    "children_count": {},
    "metadata": {},
    "geo": {
      "lat": "16.543030927787594",
      "lon": "100.61719313263893"
    },
    "source": {}
  },
  {
    "id": "65090510",
    "level": 4,
    "level_name": {
      "th": "หมู่บ้าน",
      "en": "village"
    },
    "name": {
      "th": "บ้านศาลเจ้า",
      "en": "Ban San Chao",
      "slug": "65090510"
    },
    "code": {
      "dopa": "65090510"
    },
    "parent": {
      "id": "650905",
      "level": 3,
      "name": {
        "th": "บ้านน้อยซุ้มขี้เหล็ก",
        "en": "Ban Noi Sum Khilek",
        "slug": "ban-noi-sum-khilek"
      }
    },
    "ancestors": [
      {
        "id": "65",
        "level": 1,
        "name": {
          "th": "พิษณุโลก",
          "en": "Phitsanulok",
          "slug": "phitsanulok"
        }
      },
      {
        "id": "6509",
        "level": 2,
        "name": {
          "th": "เนินมะปราง",
          "en": "Noen Maprang",
          "slug": "noen-maprang"
        }
      },
      {
        "id": "650905",
        "level": 3,
        "name": {
          "th": "บ้านน้อยซุ้มขี้เหล็ก",
          "en": "Ban Noi Sum Khilek",
          "slug": "ban-noi-sum-khilek"
        }
      }
    ],
    "children_count": {},
    "metadata": {},
    "geo": {
      "lat": "16.518987592103933",
      "lon": "100.63405618071556"
    },
    "source": {}
  },
  {
    "id": "65090511",
    "level": 4,
    "level_name": {
      "th": "หมู่บ้าน",
      "en": "village"
    },
    "name": {
      "th": "บ้านถาวรพัฒนา",
      "en": "Ban Thawon Phatthana",
      "slug": "65090511"
    },
    "code": {
      "dopa": "65090511"
    },
    "parent": {
      "id": "650905",
      "level": 3,
      "name": {
        "th": "บ้านน้อยซุ้มขี้เหล็ก",
        "en": "Ban Noi Sum Khilek",
        "slug": "ban-noi-sum-khilek"
      }
    },
    "ancestors": [
      {
        "id": "65",
        "level": 1,
        "name": {
          "th": "พิษณุโลก",
          "en": "Phitsanulok",
          "slug": "phitsanulok"
        }
      },
      {
        "id": "6509",
        "level": 2,
        "name": {
          "th": "เนินมะปราง",
          "en": "Noen Maprang",
          "slug": "noen-maprang"
        }
      },
      {
        "id": "650905",
        "level": 3,
        "name": {
          "th": "บ้านน้อยซุ้มขี้เหล็ก",
          "en": "Ban Noi Sum Khilek",
          "slug": "ban-noi-sum-khilek"
        }
      }
    ],
    "children_count": {},
    "metadata": {},
    "geo": {
      "lat": "16.545613662899612",
      "lon": "100.58486849069595"
    },
    "source": {}
  },
  {
    "id": "65090512",
    "level": 4,
    "level_name": {
      "th": "หมู่บ้าน",
      "en": "village"
    },
    "name": {
      "th": "บ้านเกาะแก้วพัฒนา",
      "en": "Ban Ko Kaeo Phatthana",
      "slug": "65090512"
    },
    "code": {
      "dopa": "65090512"
    },
    "parent": {
      "id": "650905",
      "level": 3,
      "name": {
        "th": "บ้านน้อยซุ้มขี้เหล็ก",
        "en": "Ban Noi Sum Khilek",
        "slug": "ban-noi-sum-khilek"
      }
    },
    "ancestors": [
      {
        "id": "65",
        "level": 1,
        "name": {
          "th": "พิษณุโลก",
          "en": "Phitsanulok",
          "slug": "phitsanulok"
        }
      },
      {
        "id": "6509",
        "level": 2,
        "name": {
          "th": "เนินมะปราง",
          "en": "Noen Maprang",
          "slug": "noen-maprang"
        }
      },
      {
        "id": "650905",
        "level": 3,
        "name": {
          "th": "บ้านน้อยซุ้มขี้เหล็ก",
          "en": "Ban Noi Sum Khilek",
          "slug": "ban-noi-sum-khilek"
        }
      }
    ],
    "children_count": {},
    "metadata": {},
    "geo": {
      "lat": "16.521934511310032",
      "lon": "100.5961337685585"
    },
    "source": {}
  }
]