[
  {
    "id": "33030701",
    "level": 4,
    "level_name": {
      "th": "หมู่บ้าน",
      "en": "village"
    },
    "name": {
      "th": "บ้านทาม",
      "en": "Ban Tham",
      "slug": "33030701"
    },
    "code": {
      "dopa": "33030701"
    },
    "parent": {
      "id": "330307",
      "level": 3,
      "name": {
        "th": "ทาม",
        "en": "Tham",
        "slug": "tham"
      }
    },
    "ancestors": [
      {
        "id": "33",
        "level": 1,
        "name": {
          "th": "ศรีสะเกษ",
          "en": "Si Sa Ket",
          "slug": "si-sa-ket"
        }
      },
      {
        "id": "3303",
        "level": 2,
        "name": {
          "th": "กันทรารมย์",
          "en": "Kanthararom",
          "slug": "kanthararom"
        }
      },
      {
        "id": "330307",
        "level": 3,
        "name": {
          "th": "ทาม",
          "en": "Tham",
          "slug": "tham"
        }
      }
    ],
    "children_count": {},
    "metadata": {},
    "geo": {
      "lat": "15.23456700818386",
      "lon": "104.60956200957298"
    },
    "source": {}
  },
  {
    "id": "33030702",
    "level": 4,
    "level_name": {
      "th": "หมู่บ้าน",
      "en": "village"
    },
    "name": {
      "th": "บ้านเจี่ย",
      "en": "Ban Choei",
      "slug": "33030702"
    },
    "code": {
      "dopa": "33030702"
    },
    "parent": {
      "id": "330307",
      "level": 3,
      "name": {
        "th": "ทาม",
        "en": "Tham",
        "slug": "tham"
      }
    },
    "ancestors": [
      {
        "id": "33",
        "level": 1,
        "name": {
          "th": "ศรีสะเกษ",
          "en": "Si Sa Ket",
          "slug": "si-sa-ket"
        }
      },
      {
        "id": "3303",
        "level": 2,
        "name": {
          "th": "กันทรารมย์",
          "en": "Kanthararom",
          "slug": "kanthararom"
        }
      },
      {
        "id": "330307",
        "level": 3,
        "name": {
          "th": "ทาม",
          "en": "Tham",
          "slug": "tham"
        }
      }
    ],
    "children_count": {},
    "metadata": {},
    "geo": {
      "lat": "15.22126581267206",
      "lon": "104.62347060441971"
    },
    "source": {}
  },
  {
    "id": "33030703",
    "level": 4,
    "level_name": {
      "th": "หมู่บ้าน",
      "en": "village"
    },
    "name": {
      "th": "บ้านหมัด",
      "en": "Ban Mat",
      "slug": "33030703"
    },
    "code": {
      "dopa": "33030703"
    },
    "parent": {
      "id": "330307",
      "level": 3,
      "name": {
        "th": "ทาม",
        "en": "Tham",
        "slug": "tham"
      }
    },
    "ancestors": [
      {
        "id": "33",
        "level": 1,
        "name": {
          "th": "ศรีสะเกษ",
          "en": "Si Sa Ket",
          "slug": "si-sa-ket"
        }
      },
      {
        "id": "3303",
        "level": 2,
        "name": {
          "th": "กันทรารมย์",
          "en": "Kanthararom",
          "slug": "kanthararom"
        }
      },
      {
        "id": "330307",
        "level": 3,
        "name": {
          "th": "ทาม",
          "en": "Tham",
          "slug": "tham"
        }
      }
    ],
    "children_count": {},
    "metadata": {},
    "geo": {
      "lat": "15.205680903213766",
      "lon": "104.60785210132599"
    },
    "source": {}
  },
  {
    "id": "33030704",
    "level": 4,
    "level_name": {
      "th": "หมู่บ้าน",
      "en": "village"
    },
    "name": {
      "th": "บ้านผึ้ง",
      "en": "Ban Phueng",
      "slug": "33030704"
    },
    "code": {
      "dopa": "33030704"
    },
    "parent": {
      "id": "330307",
      "level": 3,
      "name": {
        "th": "ทาม",
        "en": "Tham",
        "slug": "tham"
      }
    },
    "ancestors": [
      {
        "id": "33",
        "level": 1,
        "name": {
          "th": "ศรีสะเกษ",
          "en": "Si Sa Ket",
          "slug": "si-sa-ket"
        }
      },
      {
        "id": "3303",
        "level": 2,
        "name": {
          "th": "กันทรารมย์",
          "en": "Kanthararom",
          "slug": "kanthararom"
        }
      },
      {
        "id": "330307",
        "level": 3,
        "name": {
          "th": "ทาม",
          "en": "Tham",
          "slug": "tham"
        }
      }
    ],
    "children_count": {},
    "metadata": {},
    "geo": {
      "lat": "15.245358487824134",
      "lon": "104.58501309156418"
    },
    "source": {}
  },
  {
    "id": "33030705",
    "level": 4,
    "level_name": {
      "th": "หมู่บ้าน",
      "en": "village"
    },
    "name": {
      "th": "บ้านผึ้ง",
      "en": "Ban Phueng",
      "slug": "33030705"
    },
    "code": {
      "dopa": "33030705"
    },
    "parent": {
      "id": "330307",
      "level": 3,
      "name": {
        "th": "ทาม",
        "en": "Tham",
        "slug": "tham"
      }
    },
    "ancestors": [
      {
        "id": "33",
        "level": 1,
        "name": {
          "th": "ศรีสะเกษ",
          "en": "Si Sa Ket",
          "slug": "si-sa-ket"
        }
      },
      {
        "id": "3303",
        "level": 2,
        "name": {
          "th": "กันทรารมย์",
          "en": "Kanthararom",
          "slug": "kanthararom"
        }
      },
      {
        "id": "330307",
        "level": 3,
        "name": {
          "th": "ทาม",
          "en": "Tham",
          "slug": "tham"
        }
      }
    ],
    "children_count": {},
    "metadata": {},
    "geo": {
      "lat": "15.245358487824134",
      "lon": "104.58501309156418"
    },
    "source": {}
  },
  {
    "id": "33030706",
    "level": 4,
    "level_name": {
      "th": "หมู่บ้าน",
      "en": "village"
    },
    "name": {
      "th": "บ้านเจี่ย",
      "en": "Ban Choei",
      "slug": "33030706"
    },
    "code": {
      "dopa": "33030706"
    },
    "parent": {
      "id": "330307",
      "level": 3,
      "name": {
        "th": "ทาม",
        "en": "Tham",
        "slug": "tham"
      }
    },
    "ancestors": [
      {
        "id": "33",
        "level": 1,
        "name": {
          "th": "ศรีสะเกษ",
          "en": "Si Sa Ket",
          "slug": "si-sa-ket"
        }
      },
      {
        "id": "3303",
        "level": 2,
        "name": {
          "th": "กันทรารมย์",
          "en": "Kanthararom",
          "slug": "kanthararom"
        }
      },
      {
        "id": "330307",
        "level": 3,
        "name": {
          "th": "ทาม",
          "en": "Tham",
          "slug": "tham"
        }
      }
    ],
    "children_count": {},
    "metadata": {},
    "geo": {
      "lat": "15.216591625567844",
      "lon": "104.6200655400753"
    },
    "source": {}
  },
  {
    "id": "33030707",
    "level": 4,
    "level_name": {
      "th": "หมู่บ้าน",
      "en": "village"
    },
    "name": {
      "th": "บ้านผึ้ง",
      "en": "Ban Phueng",
      "slug": "33030707"
    },
    "code": {
      "dopa": "33030707"
    },
    "parent": {
      "id": "330307",
      "level": 3,
      "name": {
        "th": "ทาม",
        "en": "Tham",
        "slug": "tham"
      }
    },
    "ancestors": [
      {
        "id": "33",
        "level": 1,
        "name": {
          "th": "ศรีสะเกษ",
          "en": "Si Sa Ket",
          "slug": "si-sa-ket"
        }
      },
      {
        "id": "3303",
        "level": 2,
        "name": {
          "th": "กันทรารมย์",
          "en": "Kanthararom",
          "slug": "kanthararom"
        }
      },
      {
        "id": "330307",
        "level": 3,
        "name": {
          "th": "ทาม",
          "en": "Tham",
          "slug": "tham"
        }
      }
    ],
    "children_count": {},
    "metadata": {},
    "geo": {
      "lat": "15.249135374850642",
      "lon": "104.58438143134117"
    },
    "source": {}
  },
  {
    "id": "33030708",
    "level": 4,
    "level_name": {
      "th": "หมู่บ้าน",
      "en": "village"
    },
    "name": {
      "th": "บ้านผึ้ง",
      "en": "Ban Phueng",
      "slug": "33030708"
    },
    "code": {
      "dopa": "33030708"
    },
    "parent": {
      "id": "330307",
      "level": 3,
      "name": {
        "th": "ทาม",
        "en": "Tham",
        "slug": "tham"
      }
    },
    "ancestors": [
      {
        "id": "33",
        "level": 1,
        "name": {
          "th": "ศรีสะเกษ",
          "en": "Si Sa Ket",
          "slug": "si-sa-ket"
        }
      },
      {
        "id": "3303",
        "level": 2,
        "name": {
          "th": "กันทรารมย์",
          "en": "Kanthararom",
          "slug": "kanthararom"
        }
      },
      {
        "id": "330307",
        "level": 3,
        "name": {
          "th": "ทาม",
          "en": "Tham",
          "slug": "tham"
        }
      }
    ],
    "children_count": {},
    "metadata": {},
    "geo": {
      "lat": "15.246491949228362",
      "lon": "104.58546236157417"
    },
    "source": {}
  },
  {
    "id": "33030709",
    "level": 4,
    "level_name": {
      "th": "หมู่บ้าน",
      "en": "village"
    },
    "name": {
      "th": "บ้านทาม",
      "en": "Ban Tham",
      "slug": "33030709"
    },
    "code": {
      "dopa": "33030709"
    },
    "parent": {
      "id": "330307",
      "level": 3,
      "name": {
        "th": "ทาม",
        "en": "Tham",
        "slug": "tham"
      }
    },
    "ancestors": [
      {
        "id": "33",
        "level": 1,
        "name": {
          "th": "ศรีสะเกษ",
          "en": "Si Sa Ket",
          "slug": "si-sa-ket"
        }
      },
      {
        "id": "3303",
        "level": 2,
        "name": {
          "th": "กันทรารมย์",
          "en": "Kanthararom",
          "slug": "kanthararom"
        }
      },
      {
        "id": "330307",
        "level": 3,
        "name": {
          "th": "ทาม",
          "en": "Tham",
          "slug": "tham"
        }
      }
    ],
    "children_count": {},
    "metadata": {},
    "geo": {
      "lat": "15.23415034762874",
      "lon": "104.60600405931473"
    },
    "source": {}
  },
  {
    "id": "33030710",
    "level": 4,
    "level_name": {
      "th": "หมู่บ้าน",
      "en": "village"
    },
    "name": {
      "th": "บ้านหมัด",
      "en": "Ban Mat",
      "slug": "33030710"
    },
    "code": {
      "dopa": "33030710"
    },
    "parent": {
      "id": "330307",
      "level": 3,
      "name": {
        "th": "ทาม",
        "en": "Tham",
        "slug": "tham"
      }
    },
    "ancestors": [
      {
        "id": "33",
        "level": 1,
        "name": {
          "th": "ศรีสะเกษ",
          "en": "Si Sa Ket",
          "slug": "si-sa-ket"
        }
      },
      {
        "id": "3303",
        "level": 2,
        "name": {
          "th": "กันทรารมย์",
          "en": "Kanthararom",
          "slug": "kanthararom"
        }
      },
      {
        "id": "330307",
        "level": 3,
        "name": {
          "th": "ทาม",
          "en": "Tham",
          "slug": "tham"
        }
      }
    ],
    "children_count": {},
    "metadata": {},
    "geo": {
      "lat": "15.205150299774763",
      "lon": "104.60733577609062"
    },
    "source": {}
  },
  {
    "id": "33030711",
    "level": 4,
    "level_name": {
      "th": "หมู่บ้าน",
      "en": "village"
    },
    "name": {
      "th": "บ้านเจี่ย",
      "en": "Ban Choei",
      "slug": "33030711"
    },
    "code": {
      "dopa": "33030711"
    },
    "parent": {
      "id": "330307",
      "level": 3,
      "name": {
        "th": "ทาม",
        "en": "Tham",
        "slug": "tham"
      }
    },
    "ancestors": [
      {
        "id": "33",
        "level": 1,
        "name": {
          "th": "ศรีสะเกษ",
          "en": "Si Sa Ket",
          "slug": "si-sa-ket"
        }
      },
      {
        "id": "3303",
        "level": 2,
        "name": {
          "th": "กันทรารมย์",
          "en": "Kanthararom",
          "slug": "kanthararom"
        }
      },
      {
        "id": "330307",
        "level": 3,
        "name": {
          "th": "ทาม",
          "en": "Tham",
          "slug": "tham"
        }
      }
    ],
    "children_count": {},
    "metadata": {},
    "geo": {
      "lat": "15.218386515332387",
      "lon": "104.62437853217125"
    },
    "source": {}
  },
  {
    "id": "33030712",
    "level": 4,
    "level_name": {
      "th": "หมู่บ้าน",
      "en": "village"
    },
    "name": {
      "th": "บ้านผึ้ง",
      "en": "Ban Phueng",
      "slug": "33030712"
    },
    "code": {
      "dopa": "33030712"
    },
    "parent": {
      "id": "330307",
      "level": 3,
      "name": {
        "th": "ทาม",
        "en": "Tham",
        "slug": "tham"
      }
    },
    "ancestors": [
      {
        "id": "33",
        "level": 1,
        "name": {
          "th": "ศรีสะเกษ",
          "en": "Si Sa Ket",
          "slug": "si-sa-ket"
        }
      },
      {
        "id": "3303",
        "level": 2,
        "name": {
          "th": "กันทรารมย์",
          "en": "Kanthararom",
          "slug": "kanthararom"
        }
      },
      {
        "id": "330307",
        "level": 3,
        "name": {
          "th": "ทาม",
          "en": "Tham",
          "slug": "tham"
        }
      }
    ],
    "children_count": {},
    "metadata": {},
    "geo": {
      "lat": "15.243210587578677",
      "lon": "104.58587005734444"
    },
    "source": {}
  }
]