[
  {
    "id": "40040701",
    "level": 4,
    "level_name": {
      "th": "หมู่บ้าน",
      "en": "village"
    },
    "name": {
      "th": "บ้านหนองไผ่",
      "en": "Ban Nong Phai",
      "slug": "40040701"
    },
    "code": {
      "dopa": "40040701"
    },
    "parent": {
      "id": "400407",
      "level": 3,
      "name": {
        "th": "กุดกว้าง",
        "en": "Kut Kwang",
        "slug": "kut-kwang"
      }
    },
    "ancestors": [
      {
        "id": "40",
        "level": 1,
        "name": {
          "th": "ขอนแก่น",
          "en": "Khon Kaen",
          "slug": "khon-kaen"
        }
      },
      {
        "id": "4004",
        "level": 2,
        "name": {
          "th": "หนองเรือ",
          "en": "Nong Ruea",
          "slug": "nong-ruea"
        }
      },
      {
        "id": "400407",
        "level": 3,
        "name": {
          "th": "กุดกว้าง",
          "en": "Kut Kwang",
          "slug": "kut-kwang"
        }
      }
    ],
    "children_count": {},
    "metadata": {},
    "geo": {
      "lat": "16.482103587591677",
      "lon": "102.39569082856178"
    },
    "source": {}
  },
  {
    "id": "40040702",
    "level": 4,
    "level_name": {
      "th": "หมู่บ้าน",
      "en": "village"
    },
    "name": {
      "th": "บ้านโคกสูง",
      "en": "Ban Khok Sung",
      "slug": "40040702"
    },
    "code": {
      "dopa": "40040702"
    },
    "parent": {
      "id": "400407",
      "level": 3,
      "name": {
        "th": "กุดกว้าง",
        "en": "Kut Kwang",
        "slug": "kut-kwang"
      }
    },
    "ancestors": [
      {
        "id": "40",
        "level": 1,
        "name": {
          "th": "ขอนแก่น",
          "en": "Khon Kaen",
          "slug": "khon-kaen"
        }
      },
      {
        "id": "4004",
        "level": 2,
        "name": {
          "th": "หนองเรือ",
          "en": "Nong Ruea",
          "slug": "nong-ruea"
        }
      },
      {
        "id": "400407",
        "level": 3,
        "name": {
          "th": "กุดกว้าง",
          "en": "Kut Kwang",
          "slug": "kut-kwang"
        }
      }
    ],
    "children_count": {},
    "metadata": {},
    "geo": {
      "lat": "16.460572239814834",
      "lon": "102.38711044192314"
    },
    "source": {}
  },
  {
    "id": "40040703",
    "level": 4,
    "level_name": {
      "th": "หมู่บ้าน",
      "en": "village"
    },
    "name": {
      "th": "บ้านขนวน",
      "en": "Ban Khanuan",
      "slug": "40040703"
    },
    "code": {
      "dopa": "40040703"
    },
    "parent": {
      "id": "400407",
      "level": 3,
      "name": {
        "th": "กุดกว้าง",
        "en": "Kut Kwang",
        "slug": "kut-kwang"
      }
    },
    "ancestors": [
      {
        "id": "40",
        "level": 1,
        "name": {
          "th": "ขอนแก่น",
          "en": "Khon Kaen",
          "slug": "khon-kaen"
        }
      },
      {
        "id": "4004",
        "level": 2,
        "name": {
          "th": "หนองเรือ",
          "en": "Nong Ruea",
          "slug": "nong-ruea"
        }
      },
      {
        "id": "400407",
        "level": 3,
        "name": {
          "th": "กุดกว้าง",
          "en": "Kut Kwang",
          "slug": "kut-kwang"
        }
      }
    ],
    "children_count": {},
    "metadata": {},
    "geo": {
      "lat": "16.451358119194897",
      "lon": "102.38448992371559"
    },
    "source": {}
  },
  {
    "id": "40040704",
    "level": 4,
    "level_name": {
      "th": "หมู่บ้าน",
      "en": "village"
    },
    "name": {
      "th": "บ้านกุดกว้าง",
      "en": "Ban Kut Kwang",
      "slug": "40040704"
    },
    "code": {
      "dopa": "40040704"
    },
    "parent": {
      "id": "400407",
      "level": 3,
      "name": {
        "th": "กุดกว้าง",
        "en": "Kut Kwang",
        "slug": "kut-kwang"
      }
    },
    "ancestors": [
      {
        "id": "40",
        "level": 1,
        "name": {
          "th": "ขอนแก่น",
          "en": "Khon Kaen",
          "slug": "khon-kaen"
        }
      },
      {
        "id": "4004",
        "level": 2,
        "name": {
          "th": "หนองเรือ",
          "en": "Nong Ruea",
          "slug": "nong-ruea"
        }
      },
      {
        "id": "400407",
        "level": 3,
        "name": {
          "th": "กุดกว้าง",
          "en": "Kut Kwang",
          "slug": "kut-kwang"
        }
      }
    ],
    "children_count": {},
    "metadata": {},
    "geo": {
      "lat": "16.46734235875389",
      "lon": "102.36209079623222"
    },
    "source": {}
  },
  {
    "id": "40040705",
    "level": 4,
    "level_name": {
      "th": "หมู่บ้าน",
      "en": "village"
    },
    "name": {
      "th": "บ้านโนนดู่",
      "en": "Ban Non Du",
      "slug": "40040705"
    },
    "code": {
      "dopa": "40040705"
    },
    "parent": {
      "id": "400407",
      "level": 3,
      "name": {
        "th": "กุดกว้าง",
        "en": "Kut Kwang",
        "slug": "kut-kwang"
      }
    },
    "ancestors": [
      {
        "id": "40",
        "level": 1,
        "name": {
          "th": "ขอนแก่น",
          "en": "Khon Kaen",
          "slug": "khon-kaen"
        }
      },
      {
        "id": "4004",
        "level": 2,
        "name": {
          "th": "หนองเรือ",
          "en": "Nong Ruea",
          "slug": "nong-ruea"
        }
      },
      {
        "id": "400407",
        "level": 3,
        "name": {
          "th": "กุดกว้าง",
          "en": "Kut Kwang",
          "slug": "kut-kwang"
        }
      }
    ],
    "children_count": {},
    "metadata": {},
    "geo": {
      "lat": "16.477944630647944",
      "lon": "102.33164638280869"
    },
    "source": {}
  },
  {
    "id": "40040706",
    "level": 4,
    "level_name": {
      "th": "หมู่บ้าน",
      "en": "village"
    },
    "name": {
      "th": "บ้านโคกกลาง",
      "en": "Ban Khok Klang",
      "slug": "40040706"
    },
    "code": {
      "dopa": "40040706"
    },
    "parent": {
      "id": "400407",
      "level": 3,
      "name": {
        "th": "กุดกว้าง",
        "en": "Kut Kwang",
        "slug": "kut-kwang"
      }
    },
    "ancestors": [
      {
        "id": "40",
        "level": 1,
        "name": {
          "th": "ขอนแก่น",
          "en": "Khon Kaen",
          "slug": "khon-kaen"
        }
      },
      {
        "id": "4004",
        "level": 2,
        "name": {
          "th": "หนองเรือ",
          "en": "Nong Ruea",
          "slug": "nong-ruea"
        }
      },
      {
        "id": "400407",
        "level": 3,
        "name": {
          "th": "กุดกว้าง",
          "en": "Kut Kwang",
          "slug": "kut-kwang"
        }
      }
    ],
    "children_count": {},
    "metadata": {},
    "geo": {
      "lat": "16.473363759020238",
      "lon": "102.32234045863152"
    },
    "source": {}
  },
  {
    "id": "40040707",
    "level": 4,
    "level_name": {
      "th": "หมู่บ้าน",
      "en": "village"
    },
    "name": {
      "th": "บ้านหนองโก",
      "en": "Ban Nong Ko",
      "slug": "40040707"
    },
    "code": {
      "dopa": "40040707"
    },
    "parent": {
      "id": "400407",
      "level": 3,
      "name": {
        "th": "กุดกว้าง",
        "en": "Kut Kwang",
        "slug": "kut-kwang"
      }
    },
    "ancestors": [
      {
        "id": "40",
        "level": 1,
        "name": {
          "th": "ขอนแก่น",
          "en": "Khon Kaen",
          "slug": "khon-kaen"
        }
      },
      {
        "id": "4004",
        "level": 2,
        "name": {
          "th": "หนองเรือ",
          "en": "Nong Ruea",
          "slug": "nong-ruea"
        }
      },
      {
        "id": "400407",
        "level": 3,
        "name": {
          "th": "กุดกว้าง",
          "en": "Kut Kwang",
          "slug": "kut-kwang"
        }
      }
    ],
    "children_count": {},
    "metadata": {},
    "geo": {
      "lat": "16.495846543075697",
      "lon": "102.3093692958355"
    },
    "source": {}
  },
  {
    "id": "40040708",
    "level": 4,
    "level_name": {
      "th": "หมู่บ้าน",
      "en": "village"
    },
    "name": {
      "th": "บ้านสำราญหินลาด",
      "en": "Ban Samran Hin Lat",
      "slug": "40040708"
    },
    "code": {
      "dopa": "40040708"
    },
    "parent": {
      "id": "400407",
      "level": 3,
      "name": {
        "th": "กุดกว้าง",
        "en": "Kut Kwang",
        "slug": "kut-kwang"
      }
    },
    "ancestors": [
      {
        "id": "40",
        "level": 1,
        "name": {
          "th": "ขอนแก่น",
          "en": "Khon Kaen",
          "slug": "khon-kaen"
        }
      },
      {
        "id": "4004",
        "level": 2,
        "name": {
          "th": "หนองเรือ",
          "en": "Nong Ruea",
          "slug": "nong-ruea"
        }
      },
      {
        "id": "400407",
        "level": 3,
        "name": {
          "th": "กุดกว้าง",
          "en": "Kut Kwang",
          "slug": "kut-kwang"
        }
      }
    ],
    "children_count": {},
    "metadata": {},
    "geo": {
      "lat": "16.487508554931196",
      "lon": "102.31292724609375"
    },
    "source": {}
  },
  {
    "id": "40040709",
    "level": 4,
    "level_name": {
      "th": "หมู่บ้าน",
      "en": "village"
    },
    "name": {
      "th": "บ้านบะยาว",
      "en": "Ban Ba Yao",
      "slug": "40040709"
    },
    "code": {
      "dopa": "40040709"
    },
    "parent": {
      "id": "400407",
      "level": 3,
      "name": {
        "th": "กุดกว้าง",
        "en": "Kut Kwang",
        "slug": "kut-kwang"
      }
    },
    "ancestors": [
      {
        "id": "40",
        "level": 1,
        "name": {
          "th": "ขอนแก่น",
          "en": "Khon Kaen",
          "slug": "khon-kaen"
        }
      },
      {
        "id": "4004",
        "level": 2,
        "name": {
          "th": "หนองเรือ",
          "en": "Nong Ruea",
          "slug": "nong-ruea"
        }
      },
      {
        "id": "400407",
        "level": 3,
        "name": {
          "th": "กุดกว้าง",
          "en": "Kut Kwang",
          "slug": "kut-kwang"
        }
      }
    ],
    "children_count": {},
    "metadata": {},
    "geo": {
      "lat": "16.475835539816106",
      "lon": "102.29982197284698"
    },
    "source": {}
  },
  {
    "id": "40040710",
    "level": 4,
    "level_name": {
      "th": "หมู่บ้าน",
      "en": "village"
    },
    "name": {
      "th": "บ้านโนนฟันเรือ",
      "en": "Ban Non Fan Ruea",
      "slug": "40040710"
    },
    "code": {
      "dopa": "40040710"
    },
    "parent": {
      "id": "400407",
      "level": 3,
      "name": {
        "th": "กุดกว้าง",
        "en": "Kut Kwang",
        "slug": "kut-kwang"
      }
    },
    "ancestors": [
      {
        "id": "40",
        "level": 1,
        "name": {
          "th": "ขอนแก่น",
          "en": "Khon Kaen",
          "slug": "khon-kaen"
        }
      },
      {
        "id": "4004",
        "level": 2,
        "name": {
          "th": "หนองเรือ",
          "en": "Nong Ruea",
          "slug": "nong-ruea"
        }
      },
      {
        "id": "400407",
        "level": 3,
        "name": {
          "th": "กุดกว้าง",
          "en": "Kut Kwang",
          "slug": "kut-kwang"
        }
      }
    ],
    "children_count": {},
    "metadata": {},
    "geo": {
      "lat": "16.472323338214697",
      "lon": "102.29702174663544"
    },
    "source": {}
  },
  {
    "id": "40040711",
    "level": 4,
    "level_name": {
      "th": "หมู่บ้าน",
      "en": "village"
    },
    "name": {
      "th": "บ้านหนองตาไก้",
      "en": "Ban Nong Takai",
      "slug": "40040711"
    },
    "code": {
      "dopa": "40040711"
    },
    "parent": {
      "id": "400407",
      "level": 3,
      "name": {
        "th": "กุดกว้าง",
        "en": "Kut Kwang",
        "slug": "kut-kwang"
      }
    },
    "ancestors": [
      {
        "id": "40",
        "level": 1,
        "name": {
          "th": "ขอนแก่น",
          "en": "Khon Kaen",
          "slug": "khon-kaen"
        }
      },
      {
        "id": "4004",
        "level": 2,
        "name": {
          "th": "หนองเรือ",
          "en": "Nong Ruea",
          "slug": "nong-ruea"
        }
      },
      {
        "id": "400407",
        "level": 3,
        "name": {
          "th": "กุดกว้าง",
          "en": "Kut Kwang",
          "slug": "kut-kwang"
        }
      }
    ],
    "children_count": {},
    "metadata": {},
    "geo": {
      "lat": "16.513210625731524",
      "lon": "102.29289919137955"
    },
    "source": {}
  },
  {
    "id": "40040712",
    "level": 4,
    "level_name": {
      "th": "หมู่บ้าน",
      "en": "village"
    },
    "name": {
      "th": "บ้าน กม.52",
      "en": "Ban km.52",
      "slug": "40040712"
    },
    "code": {
      "dopa": "40040712"
    },
    "parent": {
      "id": "400407",
      "level": 3,
      "name": {
        "th": "กุดกว้าง",
        "en": "Kut Kwang",
        "slug": "kut-kwang"
      }
    },
    "ancestors": [
      {
        "id": "40",
        "level": 1,
        "name": {
          "th": "ขอนแก่น",
          "en": "Khon Kaen",
          "slug": "khon-kaen"
        }
      },
      {
        "id": "4004",
        "level": 2,
        "name": {
          "th": "หนองเรือ",
          "en": "Nong Ruea",
          "slug": "nong-ruea"
        }
      },
      {
        "id": "400407",
        "level": 3,
        "name": {
          "th": "กุดกว้าง",
          "en": "Kut Kwang",
          "slug": "kut-kwang"
        }
      }
    ],
    "children_count": {},
    "metadata": {},
    "geo": {
      "lat": "16.490266920505476",
      "lon": "102.36204117536545"
    },
    "source": {}
  },
  {
    "id": "40040713",
    "level": 4,
    "level_name": {
      "th": "หมู่บ้าน",
      "en": "village"
    },
    "name": {
      "th": "บ้านโนนสะทอน",
      "en": "Ban Non Sathon",
      "slug": "40040713"
    },
    "code": {
      "dopa": "40040713"
    },
    "parent": {
      "id": "400407",
      "level": 3,
      "name": {
        "th": "กุดกว้าง",
        "en": "Kut Kwang",
        "slug": "kut-kwang"
      }
    },
    "ancestors": [
      {
        "id": "40",
        "level": 1,
        "name": {
          "th": "ขอนแก่น",
          "en": "Khon Kaen",
          "slug": "khon-kaen"
        }
      },
      {
        "id": "4004",
        "level": 2,
        "name": {
          "th": "หนองเรือ",
          "en": "Nong Ruea",
          "slug": "nong-ruea"
        }
      },
      {
        "id": "400407",
        "level": 3,
        "name": {
          "th": "กุดกว้าง",
          "en": "Kut Kwang",
          "slug": "kut-kwang"
        }
      }
    ],
    "children_count": {},
    "metadata": {},
    "geo": {
      "lat": "16.49119536851363",
      "lon": "102.31138363480568"
    },
    "source": {}
  },
  {
    "id": "40040714",
    "level": 4,
    "level_name": {
      "th": "หมู่บ้าน",
      "en": "village"
    },
    "name": {
      "th": "บ้านหนองดินกี่",
      "en": "Ban Nong Din Ki",
      "slug": "40040714"
    },
    "code": {
      "dopa": "40040714"
    },
    "parent": {
      "id": "400407",
      "level": 3,
      "name": {
        "th": "กุดกว้าง",
        "en": "Kut Kwang",
        "slug": "kut-kwang"
      }
    },
    "ancestors": [
      {
        "id": "40",
        "level": 1,
        "name": {
          "th": "ขอนแก่น",
          "en": "Khon Kaen",
          "slug": "khon-kaen"
        }
      },
      {
        "id": "4004",
        "level": 2,
        "name": {
          "th": "หนองเรือ",
          "en": "Nong Ruea",
          "slug": "nong-ruea"
        }
      },
      {
        "id": "400407",
        "level": 3,
        "name": {
          "th": "กุดกว้าง",
          "en": "Kut Kwang",
          "slug": "kut-kwang"
        }
      }
    ],
    "children_count": {},
    "metadata": {},
    "geo": {
      "lat": "16.47928209098411",
      "lon": "102.35532760620117"
    },
    "source": {}
  },
  {
    "id": "40040715",
    "level": 4,
    "level_name": {
      "th": "หมู่บ้าน",
      "en": "village"
    },
    "name": {
      "th": "บ้านหนองกุง",
      "en": "Ban Nong Kung",
      "slug": "40040715"
    },
    "code": {
      "dopa": "40040715"
    },
    "parent": {
      "id": "400407",
      "level": 3,
      "name": {
        "th": "กุดกว้าง",
        "en": "Kut Kwang",
        "slug": "kut-kwang"
      }
    },
    "ancestors": [
      {
        "id": "40",
        "level": 1,
        "name": {
          "th": "ขอนแก่น",
          "en": "Khon Kaen",
          "slug": "khon-kaen"
        }
      },
      {
        "id": "4004",
        "level": 2,
        "name": {
          "th": "หนองเรือ",
          "en": "Nong Ruea",
          "slug": "nong-ruea"
        }
      },
      {
        "id": "400407",
        "level": 3,
        "name": {
          "th": "กุดกว้าง",
          "en": "Kut Kwang",
          "slug": "kut-kwang"
        }
      }
    ],
    "children_count": {},
    "metadata": {},
    "geo": {
      "lat": "16.48165606033488",
      "lon": "102.37786889076233"
    },
    "source": {}
  },
  {
    "id": "40040716",
    "level": 4,
    "level_name": {
      "th": "หมู่บ้าน",
      "en": "village"
    },
    "name": {
      "th": "บ้านโนนสง่า",
      "en": "Ban Non Sa-nga",
      "slug": "40040716"
    },
    "code": {
      "dopa": "40040716"
    },
    "parent": {
      "id": "400407",
      "level": 3,
      "name": {
        "th": "กุดกว้าง",
        "en": "Kut Kwang",
        "slug": "kut-kwang"
      }
    },
    "ancestors": [
      {
        "id": "40",
        "level": 1,
        "name": {
          "th": "ขอนแก่น",
          "en": "Khon Kaen",
          "slug": "khon-kaen"
        }
      },
      {
        "id": "4004",
        "level": 2,
        "name": {
          "th": "หนองเรือ",
          "en": "Nong Ruea",
          "slug": "nong-ruea"
        }
      },
      {
        "id": "400407",
        "level": 3,
        "name": {
          "th": "กุดกว้าง",
          "en": "Kut Kwang",
          "slug": "kut-kwang"
        }
      }
    ],
    "children_count": {},
    "metadata": {},
    "geo": {
      "lat": "16.48343330328144",
      "lon": "102.34691217541695"
    },
    "source": {}
  },
  {
    "id": "40040717",
    "level": 4,
    "level_name": {
      "th": "หมู่บ้าน",
      "en": "village"
    },
    "name": {
      "th": "บ้านขนวนนคร",
      "en": "Ban Khanuan Nakhon",
      "slug": "40040717"
    },
    "code": {
      "dopa": "40040717"
    },
    "parent": {
      "id": "400407",
      "level": 3,
      "name": {
        "th": "กุดกว้าง",
        "en": "Kut Kwang",
        "slug": "kut-kwang"
      }
    },
    "ancestors": [
      {
        "id": "40",
        "level": 1,
        "name": {
          "th": "ขอนแก่น",
          "en": "Khon Kaen",
          "slug": "khon-kaen"
        }
      },
      {
        "id": "4004",
        "level": 2,
        "name": {
          "th": "หนองเรือ",
          "en": "Nong Ruea",
          "slug": "nong-ruea"
        }
      },
      {
        "id": "400407",
        "level": 3,
        "name": {
          "th": "กุดกว้าง",
          "en": "Kut Kwang",
          "slug": "kut-kwang"
        }
      }
    ],
    "children_count": {},
    "metadata": {},
    "geo": {
      "lat": "16.450920810576566",
      "lon": "102.38716408610344"
    },
    "source": {}
  },
  {
    "id": "40040718",
    "level": 4,
    "level_name": {
      "th": "หมู่บ้าน",
      "en": "village"
    },
    "name": {
      "th": "บ้านหนองแวง",
      "en": "Ban Nong Waeng",
      "slug": "40040718"
    },
    "code": {
      "dopa": "40040718"
    },
    "parent": {
      "id": "400407",
      "level": 3,
      "name": {
        "th": "กุดกว้าง",
        "en": "Kut Kwang",
        "slug": "kut-kwang"
      }
    },
    "ancestors": [
      {
        "id": "40",
        "level": 1,
        "name": {
          "th": "ขอนแก่น",
          "en": "Khon Kaen",
          "slug": "khon-kaen"
        }
      },
      {
        "id": "4004",
        "level": 2,
        "name": {
          "th": "หนองเรือ",
          "en": "Nong Ruea",
          "slug": "nong-ruea"
        }
      },
      {
        "id": "400407",
        "level": 3,
        "name": {
          "th": "กุดกว้าง",
          "en": "Kut Kwang",
          "slug": "kut-kwang"
        }
      }
    ],
    "children_count": {},
    "metadata": {},
    "geo": {
      "lat": "16.48186825011144",
      "lon": "102.34254688024521"
    },
    "source": {}
  },
  {
    "id": "40040719",
    "level": 4,
    "level_name": {
      "th": "หมู่บ้าน",
      "en": "village"
    },
    "name": {
      "th": "บ้านบะยาวสันติสุข",
      "en": "Ban Ba Yao Santi Suk",
      "slug": "40040719"
    },
    "code": {
      "dopa": "40040719"
    },
    "parent": {
      "id": "400407",
      "level": 3,
      "name": {
        "th": "กุดกว้าง",
        "en": "Kut Kwang",
        "slug": "kut-kwang"
      }
    },
    "ancestors": [
      {
        "id": "40",
        "level": 1,
        "name": {
          "th": "ขอนแก่น",
          "en": "Khon Kaen",
          "slug": "khon-kaen"
        }
      },
      {
        "id": "4004",
        "level": 2,
        "name": {
          "th": "หนองเรือ",
          "en": "Nong Ruea",
          "slug": "nong-ruea"
        }
      },
      {
        "id": "400407",
        "level": 3,
        "name": {
          "th": "กุดกว้าง",
          "en": "Kut Kwang",
          "slug": "kut-kwang"
        }
      }
    ],
    "children_count": {},
    "metadata": {},
    "geo": {
      "lat": "16.477643700799614",
      "lon": "102.30040803551674"
    },
    "source": {}
  },
  {
    "id": "40040720",
    "level": 4,
    "level_name": {
      "th": "หมู่บ้าน",
      "en": "village"
    },
    "name": {
      "th": "บ้านโนนฟันเรือ",
      "en": "Ban Non Fan Ruea",
      "slug": "40040720"
    },
    "code": {
      "dopa": "40040720"
    },
    "parent": {
      "id": "400407",
      "level": 3,
      "name": {
        "th": "กุดกว้าง",
        "en": "Kut Kwang",
        "slug": "kut-kwang"
      }
    },
    "ancestors": [
      {
        "id": "40",
        "level": 1,
        "name": {
          "th": "ขอนแก่น",
          "en": "Khon Kaen",
          "slug": "khon-kaen"
        }
      },
      {
        "id": "4004",
        "level": 2,
        "name": {
          "th": "หนองเรือ",
          "en": "Nong Ruea",
          "slug": "nong-ruea"
        }
      },
      {
        "id": "400407",
        "level": 3,
        "name": {
          "th": "กุดกว้าง",
          "en": "Kut Kwang",
          "slug": "kut-kwang"
        }
      }
    ],
    "children_count": {},
    "metadata": {},
    "geo": {
      "lat": "16.475054913179896",
      "lon": "102.30015993118286"
    },
    "source": {}
  },
  {
    "id": "40040721",
    "level": 4,
    "level_name": {
      "th": "หมู่บ้าน",
      "en": "village"
    },
    "name": {
      "th": "บ้านหนองไผ่พัฒนา",
      "en": "Ban Nong Phai Phatthana",
      "slug": "40040721"
    },
    "code": {
      "dopa": "40040721"
    },
    "parent": {
      "id": "400407",
      "level": 3,
      "name": {
        "th": "กุดกว้าง",
        "en": "Kut Kwang",
        "slug": "kut-kwang"
      }
    },
    "ancestors": [
      {
        "id": "40",
        "level": 1,
        "name": {
          "th": "ขอนแก่น",
          "en": "Khon Kaen",
          "slug": "khon-kaen"
        }
      },
      {
        "id": "4004",
        "level": 2,
        "name": {
          "th": "หนองเรือ",
          "en": "Nong Ruea",
          "slug": "nong-ruea"
        }
      },
      {
        "id": "400407",
        "level": 3,
        "name": {
          "th": "กุดกว้าง",
          "en": "Kut Kwang",
          "slug": "kut-kwang"
        }
      }
    ],
    "children_count": {},
    "metadata": {},
    "geo": {
      "lat": "16.48245595027877",
      "lon": "102.39723980426788"
    },
    "source": {}
  }
]