{
  "id": "321303",
  "level": 3,
  "level_name": {
    "th": "ตำบล",
    "en": "subdistrict"
  },
  "name": {
    "th": "จรัส",
    "en": "Charat",
    "slug": "charat"
  },
  "code": {
    "dopa": "321303"
  },
  "parent": {
    "id": "3213",
    "level": 2,
    "name": {
      "th": "บัวเชด",
      "en": "Buachet",
      "slug": "buachet"
    }
  },
  "ancestors": [
    {
      "id": "32",
      "level": 1,
      "name": {
        "th": "สุรินทร์",
        "en": "Surin",
        "slug": "surin"
      }
    },
    {
      "id": "3213",
      "level": 2,
      "name": {
        "th": "บัวเชด",
        "en": "Buachet",
        "slug": "buachet"
      }
    }
  ],
  "children_count": {
    "villages": 12
  },
  "zip_codes": [
    "32230"
  ],
  "metadata": {
    "is_special_province": false
  },
  "geo": {
    "lat": "14.413",
    "lon": "103.976"
  },
  "source": {
    "url": "https://thaiaddress.org/subdistrict/charat-321303/"
  }
}