[
  {
    "id": "54011501",
    "level": 4,
    "level_name": {
      "th": "หมู่บ้าน",
      "en": "village"
    },
    "name": {
      "th": "บ้านทุ่งกวาว",
      "en": "Ban Thung Kwao",
      "slug": "54011501"
    },
    "code": {
      "dopa": "54011501"
    },
    "parent": {
      "id": "540115",
      "level": 3,
      "name": {
        "th": "ทุ่งกวาว",
        "en": "Thung Kwao",
        "slug": "thung-kwao"
      }
    },
    "ancestors": [
      {
        "id": "54",
        "level": 1,
        "name": {
          "th": "แพร่",
          "en": "Phrae",
          "slug": "phrae"
        }
      },
      {
        "id": "5401",
        "level": 2,
        "name": {
          "th": "เมืองแพร่",
          "en": "Mueang Phrae",
          "slug": "mueang-phrae"
        }
      },
      {
        "id": "540115",
        "level": 3,
        "name": {
          "th": "ทุ่งกวาว",
          "en": "Thung Kwao",
          "slug": "thung-kwao"
        }
      }
    ],
    "children_count": {},
    "metadata": {},
    "geo": {
      "lat": "18.157626896588866",
      "lon": "100.1593641936779"
    },
    "source": {}
  },
  {
    "id": "54011502",
    "level": 4,
    "level_name": {
      "th": "หมู่บ้าน",
      "en": "village"
    },
    "name": {
      "th": "บ้านนาแหลมใต้",
      "en": "Ban Na Laem Tai",
      "slug": "54011502"
    },
    "code": {
      "dopa": "54011502"
    },
    "parent": {
      "id": "540115",
      "level": 3,
      "name": {
        "th": "ทุ่งกวาว",
        "en": "Thung Kwao",
        "slug": "thung-kwao"
      }
    },
    "ancestors": [
      {
        "id": "54",
        "level": 1,
        "name": {
          "th": "แพร่",
          "en": "Phrae",
          "slug": "phrae"
        }
      },
      {
        "id": "5401",
        "level": 2,
        "name": {
          "th": "เมืองแพร่",
          "en": "Mueang Phrae",
          "slug": "mueang-phrae"
        }
      },
      {
        "id": "540115",
        "level": 3,
        "name": {
          "th": "ทุ่งกวาว",
          "en": "Thung Kwao",
          "slug": "thung-kwao"
        }
      }
    ],
    "children_count": {},
    "metadata": {},
    "geo": {
      "lat": "18.151064019000543",
      "lon": "100.16340494155884"
    },
    "source": {}
  },
  {
    "id": "54011503",
    "level": 4,
    "level_name": {
      "th": "หมู่บ้าน",
      "en": "village"
    },
    "name": {
      "th": "บ้านนาแหลมเหนือ",
      "en": "Ban Na Laem Nuea",
      "slug": "54011503"
    },
    "code": {
      "dopa": "54011503"
    },
    "parent": {
      "id": "540115",
      "level": 3,
      "name": {
        "th": "ทุ่งกวาว",
        "en": "Thung Kwao",
        "slug": "thung-kwao"
      }
    },
    "ancestors": [
      {
        "id": "54",
        "level": 1,
        "name": {
          "th": "แพร่",
          "en": "Phrae",
          "slug": "phrae"
        }
      },
      {
        "id": "5401",
        "level": 2,
        "name": {
          "th": "เมืองแพร่",
          "en": "Mueang Phrae",
          "slug": "mueang-phrae"
        }
      },
      {
        "id": "540115",
        "level": 3,
        "name": {
          "th": "ทุ่งกวาว",
          "en": "Thung Kwao",
          "slug": "thung-kwao"
        }
      }
    ],
    "children_count": {},
    "metadata": {},
    "geo": {
      "lat": "18.149815132827214",
      "lon": "100.16785204410553"
    },
    "source": {}
  },
  {
    "id": "54011504",
    "level": 4,
    "level_name": {
      "th": "หมู่บ้าน",
      "en": "village"
    },
    "name": {
      "th": "บ้านหัวดง",
      "en": "Ban Hua Dong",
      "slug": "54011504"
    },
    "code": {
      "dopa": "54011504"
    },
    "parent": {
      "id": "540115",
      "level": 3,
      "name": {
        "th": "ทุ่งกวาว",
        "en": "Thung Kwao",
        "slug": "thung-kwao"
      }
    },
    "ancestors": [
      {
        "id": "54",
        "level": 1,
        "name": {
          "th": "แพร่",
          "en": "Phrae",
          "slug": "phrae"
        }
      },
      {
        "id": "5401",
        "level": 2,
        "name": {
          "th": "เมืองแพร่",
          "en": "Mueang Phrae",
          "slug": "mueang-phrae"
        }
      },
      {
        "id": "540115",
        "level": 3,
        "name": {
          "th": "ทุ่งกวาว",
          "en": "Thung Kwao",
          "slug": "thung-kwao"
        }
      }
    ],
    "children_count": {},
    "metadata": {},
    "geo": {
      "lat": "18.155283404129598",
      "lon": "100.1490966975689"
    },
    "source": {}
  },
  {
    "id": "54011505",
    "level": 4,
    "level_name": {
      "th": "หมู่บ้าน",
      "en": "village"
    },
    "name": {
      "th": "บ้านทุ่งป่าดำ",
      "en": "Ban Thung Pa Dam",
      "slug": "54011505"
    },
    "code": {
      "dopa": "54011505"
    },
    "parent": {
      "id": "540115",
      "level": 3,
      "name": {
        "th": "ทุ่งกวาว",
        "en": "Thung Kwao",
        "slug": "thung-kwao"
      }
    },
    "ancestors": [
      {
        "id": "54",
        "level": 1,
        "name": {
          "th": "แพร่",
          "en": "Phrae",
          "slug": "phrae"
        }
      },
      {
        "id": "5401",
        "level": 2,
        "name": {
          "th": "เมืองแพร่",
          "en": "Mueang Phrae",
          "slug": "mueang-phrae"
        }
      },
      {
        "id": "540115",
        "level": 3,
        "name": {
          "th": "ทุ่งกวาว",
          "en": "Thung Kwao",
          "slug": "thung-kwao"
        }
      }
    ],
    "children_count": {},
    "metadata": {},
    "geo": {
      "lat": "18.159557482584614",
      "lon": "100.16558557748795"
    },
    "source": {}
  },
  {
    "id": "54011506",
    "level": 4,
    "level_name": {
      "th": "หมู่บ้าน",
      "en": "village"
    },
    "name": {
      "th": "บ้านนาแหลม",
      "en": "Ban Na Laem",
      "slug": "54011506"
    },
    "code": {
      "dopa": "54011506"
    },
    "parent": {
      "id": "540115",
      "level": 3,
      "name": {
        "th": "ทุ่งกวาว",
        "en": "Thung Kwao",
        "slug": "thung-kwao"
      }
    },
    "ancestors": [
      {
        "id": "54",
        "level": 1,
        "name": {
          "th": "แพร่",
          "en": "Phrae",
          "slug": "phrae"
        }
      },
      {
        "id": "5401",
        "level": 2,
        "name": {
          "th": "เมืองแพร่",
          "en": "Mueang Phrae",
          "slug": "mueang-phrae"
        }
      },
      {
        "id": "540115",
        "level": 3,
        "name": {
          "th": "ทุ่งกวาว",
          "en": "Thung Kwao",
          "slug": "thung-kwao"
        }
      }
    ],
    "children_count": {},
    "metadata": {},
    "geo": {
      "lat": "18.151908923666923",
      "lon": "100.16592890024185"
    },
    "source": {}
  }
]