[
  {
    "id": "31050301",
    "level": 4,
    "level_name": {
      "th": "หมู่บ้าน",
      "en": "village"
    },
    "name": {
      "th": "บ้านหนองปรือ",
      "en": "Ban Nong Prue",
      "slug": "31050301"
    },
    "code": {
      "dopa": "31050301"
    },
    "parent": {
      "id": "310503",
      "level": 3,
      "name": {
        "th": "เมืองไผ่",
        "en": "Mueang Phai",
        "slug": "mueang-phai"
      }
    },
    "ancestors": [
      {
        "id": "31",
        "level": 1,
        "name": {
          "th": "บุรีรัมย์",
          "en": "Buri Ram",
          "slug": "buri-ram"
        }
      },
      {
        "id": "3105",
        "level": 2,
        "name": {
          "th": "หนองกี่",
          "en": "Nong Ki",
          "slug": "nong-ki"
        }
      },
      {
        "id": "310503",
        "level": 3,
        "name": {
          "th": "เมืองไผ่",
          "en": "Mueang Phai",
          "slug": "mueang-phai"
        }
      }
    ],
    "children_count": {},
    "metadata": {},
    "geo": {
      "lat": "14.772662439894646",
      "lon": "102.62816727161407"
    },
    "source": {}
  },
  {
    "id": "31050302",
    "level": 4,
    "level_name": {
      "th": "หมู่บ้าน",
      "en": "village"
    },
    "name": {
      "th": "บ้านสระขาม",
      "en": "Ban Sa Kham",
      "slug": "31050302"
    },
    "code": {
      "dopa": "31050302"
    },
    "parent": {
      "id": "310503",
      "level": 3,
      "name": {
        "th": "เมืองไผ่",
        "en": "Mueang Phai",
        "slug": "mueang-phai"
      }
    },
    "ancestors": [
      {
        "id": "31",
        "level": 1,
        "name": {
          "th": "บุรีรัมย์",
          "en": "Buri Ram",
          "slug": "buri-ram"
        }
      },
      {
        "id": "3105",
        "level": 2,
        "name": {
          "th": "หนองกี่",
          "en": "Nong Ki",
          "slug": "nong-ki"
        }
      },
      {
        "id": "310503",
        "level": 3,
        "name": {
          "th": "เมืองไผ่",
          "en": "Mueang Phai",
          "slug": "mueang-phai"
        }
      }
    ],
    "children_count": {},
    "metadata": {},
    "geo": {
      "lat": "14.76706808263957",
      "lon": "102.59561061859131"
    },
    "source": {}
  },
  {
    "id": "31050303",
    "level": 4,
    "level_name": {
      "th": "หมู่บ้าน",
      "en": "village"
    },
    "name": {
      "th": "บ้านโนนสำราญ",
      "en": "Ban Non Samran",
      "slug": "31050303"
    },
    "code": {
      "dopa": "31050303"
    },
    "parent": {
      "id": "310503",
      "level": 3,
      "name": {
        "th": "เมืองไผ่",
        "en": "Mueang Phai",
        "slug": "mueang-phai"
      }
    },
    "ancestors": [
      {
        "id": "31",
        "level": 1,
        "name": {
          "th": "บุรีรัมย์",
          "en": "Buri Ram",
          "slug": "buri-ram"
        }
      },
      {
        "id": "3105",
        "level": 2,
        "name": {
          "th": "หนองกี่",
          "en": "Nong Ki",
          "slug": "nong-ki"
        }
      },
      {
        "id": "310503",
        "level": 3,
        "name": {
          "th": "เมืองไผ่",
          "en": "Mueang Phai",
          "slug": "mueang-phai"
        }
      }
    ],
    "children_count": {},
    "metadata": {},
    "geo": {
      "lat": "14.799074833492456",
      "lon": "102.70324096083641"
    },
    "source": {}
  },
  {
    "id": "31050304",
    "level": 4,
    "level_name": {
      "th": "หมู่บ้าน",
      "en": "village"
    },
    "name": {
      "th": "บ้านหนองไผ่",
      "en": "Ban Nong Phai",
      "slug": "31050304"
    },
    "code": {
      "dopa": "31050304"
    },
    "parent": {
      "id": "310503",
      "level": 3,
      "name": {
        "th": "เมืองไผ่",
        "en": "Mueang Phai",
        "slug": "mueang-phai"
      }
    },
    "ancestors": [
      {
        "id": "31",
        "level": 1,
        "name": {
          "th": "บุรีรัมย์",
          "en": "Buri Ram",
          "slug": "buri-ram"
        }
      },
      {
        "id": "3105",
        "level": 2,
        "name": {
          "th": "หนองกี่",
          "en": "Nong Ki",
          "slug": "nong-ki"
        }
      },
      {
        "id": "310503",
        "level": 3,
        "name": {
          "th": "เมืองไผ่",
          "en": "Mueang Phai",
          "slug": "mueang-phai"
        }
      }
    ],
    "children_count": {},
    "metadata": {},
    "geo": {
      "lat": "14.75862440246376",
      "lon": "102.65654370188713"
    },
    "source": {}
  },
  {
    "id": "31050305",
    "level": 4,
    "level_name": {
      "th": "หมู่บ้าน",
      "en": "village"
    },
    "name": {
      "th": "บ้านสระขามใหญ่",
      "en": "Ban Sa Kham Yai",
      "slug": "31050305"
    },
    "code": {
      "dopa": "31050305"
    },
    "parent": {
      "id": "310503",
      "level": 3,
      "name": {
        "th": "เมืองไผ่",
        "en": "Mueang Phai",
        "slug": "mueang-phai"
      }
    },
    "ancestors": [
      {
        "id": "31",
        "level": 1,
        "name": {
          "th": "บุรีรัมย์",
          "en": "Buri Ram",
          "slug": "buri-ram"
        }
      },
      {
        "id": "3105",
        "level": 2,
        "name": {
          "th": "หนองกี่",
          "en": "Nong Ki",
          "slug": "nong-ki"
        }
      },
      {
        "id": "310503",
        "level": 3,
        "name": {
          "th": "เมืองไผ่",
          "en": "Mueang Phai",
          "slug": "mueang-phai"
        }
      }
    ],
    "children_count": {},
    "metadata": {},
    "geo": {
      "lat": "14.770695",
      "lon": "102.590648"
    },
    "source": {}
  },
  {
    "id": "31050306",
    "level": 4,
    "level_name": {
      "th": "หมู่บ้าน",
      "en": "village"
    },
    "name": {
      "th": "บ้านนาจาน",
      "en": "Ban Na Chan",
      "slug": "31050306"
    },
    "code": {
      "dopa": "31050306"
    },
    "parent": {
      "id": "310503",
      "level": 3,
      "name": {
        "th": "เมืองไผ่",
        "en": "Mueang Phai",
        "slug": "mueang-phai"
      }
    },
    "ancestors": [
      {
        "id": "31",
        "level": 1,
        "name": {
          "th": "บุรีรัมย์",
          "en": "Buri Ram",
          "slug": "buri-ram"
        }
      },
      {
        "id": "3105",
        "level": 2,
        "name": {
          "th": "หนองกี่",
          "en": "Nong Ki",
          "slug": "nong-ki"
        }
      },
      {
        "id": "310503",
        "level": 3,
        "name": {
          "th": "เมืองไผ่",
          "en": "Mueang Phai",
          "slug": "mueang-phai"
        }
      }
    ],
    "children_count": {},
    "metadata": {},
    "geo": {
      "lat": "14.780440354174706",
      "lon": "102.69539684057236"
    },
    "source": {}
  },
  {
    "id": "31050307",
    "level": 4,
    "level_name": {
      "th": "หมู่บ้าน",
      "en": "village"
    },
    "name": {
      "th": "บ้านหนองม่วง",
      "en": "Ban Nong Muang",
      "slug": "31050307"
    },
    "code": {
      "dopa": "31050307"
    },
    "parent": {
      "id": "310503",
      "level": 3,
      "name": {
        "th": "เมืองไผ่",
        "en": "Mueang Phai",
        "slug": "mueang-phai"
      }
    },
    "ancestors": [
      {
        "id": "31",
        "level": 1,
        "name": {
          "th": "บุรีรัมย์",
          "en": "Buri Ram",
          "slug": "buri-ram"
        }
      },
      {
        "id": "3105",
        "level": 2,
        "name": {
          "th": "หนองกี่",
          "en": "Nong Ki",
          "slug": "nong-ki"
        }
      },
      {
        "id": "310503",
        "level": 3,
        "name": {
          "th": "เมืองไผ่",
          "en": "Mueang Phai",
          "slug": "mueang-phai"
        }
      }
    ],
    "children_count": {},
    "metadata": {},
    "geo": {
      "lat": "14.79164249902959",
      "lon": "102.637789696455"
    },
    "source": {}
  },
  {
    "id": "31050308",
    "level": 4,
    "level_name": {
      "th": "หมู่บ้าน",
      "en": "village"
    },
    "name": {
      "th": "บ้านห้วยลึก",
      "en": "Ban Huai Luek",
      "slug": "31050308"
    },
    "code": {
      "dopa": "31050308"
    },
    "parent": {
      "id": "310503",
      "level": 3,
      "name": {
        "th": "เมืองไผ่",
        "en": "Mueang Phai",
        "slug": "mueang-phai"
      }
    },
    "ancestors": [
      {
        "id": "31",
        "level": 1,
        "name": {
          "th": "บุรีรัมย์",
          "en": "Buri Ram",
          "slug": "buri-ram"
        }
      },
      {
        "id": "3105",
        "level": 2,
        "name": {
          "th": "หนองกี่",
          "en": "Nong Ki",
          "slug": "nong-ki"
        }
      },
      {
        "id": "310503",
        "level": 3,
        "name": {
          "th": "เมืองไผ่",
          "en": "Mueang Phai",
          "slug": "mueang-phai"
        }
      }
    ],
    "children_count": {},
    "metadata": {},
    "geo": {
      "lat": "14.778005085188799",
      "lon": "102.69636243581772"
    },
    "source": {}
  },
  {
    "id": "31050309",
    "level": 4,
    "level_name": {
      "th": "หมู่บ้าน",
      "en": "village"
    },
    "name": {
      "th": "บ้านหนองเต่า",
      "en": "Ban Nong Tao",
      "slug": "31050309"
    },
    "code": {
      "dopa": "31050309"
    },
    "parent": {
      "id": "310503",
      "level": 3,
      "name": {
        "th": "เมืองไผ่",
        "en": "Mueang Phai",
        "slug": "mueang-phai"
      }
    },
    "ancestors": [
      {
        "id": "31",
        "level": 1,
        "name": {
          "th": "บุรีรัมย์",
          "en": "Buri Ram",
          "slug": "buri-ram"
        }
      },
      {
        "id": "3105",
        "level": 2,
        "name": {
          "th": "หนองกี่",
          "en": "Nong Ki",
          "slug": "nong-ki"
        }
      },
      {
        "id": "310503",
        "level": 3,
        "name": {
          "th": "เมืองไผ่",
          "en": "Mueang Phai",
          "slug": "mueang-phai"
        }
      }
    ],
    "children_count": {},
    "metadata": {},
    "geo": {
      "lat": "14.789361660060095",
      "lon": "102.66690373420715"
    },
    "source": {}
  },
  {
    "id": "31050310",
    "level": 4,
    "level_name": {
      "th": "หมู่บ้าน",
      "en": "village"
    },
    "name": {
      "th": "บ้านโคกกระชาย",
      "en": "Ban Khok Krachai",
      "slug": "31050310"
    },
    "code": {
      "dopa": "31050310"
    },
    "parent": {
      "id": "310503",
      "level": 3,
      "name": {
        "th": "เมืองไผ่",
        "en": "Mueang Phai",
        "slug": "mueang-phai"
      }
    },
    "ancestors": [
      {
        "id": "31",
        "level": 1,
        "name": {
          "th": "บุรีรัมย์",
          "en": "Buri Ram",
          "slug": "buri-ram"
        }
      },
      {
        "id": "3105",
        "level": 2,
        "name": {
          "th": "หนองกี่",
          "en": "Nong Ki",
          "slug": "nong-ki"
        }
      },
      {
        "id": "310503",
        "level": 3,
        "name": {
          "th": "เมืองไผ่",
          "en": "Mueang Phai",
          "slug": "mueang-phai"
        }
      }
    ],
    "children_count": {},
    "metadata": {},
    "geo": {
      "lat": "14.768132759313566",
      "lon": "102.67071783542633"
    },
    "source": {}
  },
  {
    "id": "31050311",
    "level": 4,
    "level_name": {
      "th": "หมู่บ้าน",
      "en": "village"
    },
    "name": {
      "th": "บ้านเมืองไผ่",
      "en": "Ban Mueang Phai",
      "slug": "31050311"
    },
    "code": {
      "dopa": "31050311"
    },
    "parent": {
      "id": "310503",
      "level": 3,
      "name": {
        "th": "เมืองไผ่",
        "en": "Mueang Phai",
        "slug": "mueang-phai"
      }
    },
    "ancestors": [
      {
        "id": "31",
        "level": 1,
        "name": {
          "th": "บุรีรัมย์",
          "en": "Buri Ram",
          "slug": "buri-ram"
        }
      },
      {
        "id": "3105",
        "level": 2,
        "name": {
          "th": "หนองกี่",
          "en": "Nong Ki",
          "slug": "nong-ki"
        }
      },
      {
        "id": "310503",
        "level": 3,
        "name": {
          "th": "เมืองไผ่",
          "en": "Mueang Phai",
          "slug": "mueang-phai"
        }
      }
    ],
    "children_count": {},
    "metadata": {},
    "geo": {
      "lat": "14.770879367624795",
      "lon": "102.62357667088509"
    },
    "source": {}
  },
  {
    "id": "31050312",
    "level": 4,
    "level_name": {
      "th": "หมู่บ้าน",
      "en": "village"
    },
    "name": {
      "th": "บ้านน้อยพัฒนา",
      "en": "Ban Noi Phatthana",
      "slug": "31050312"
    },
    "code": {
      "dopa": "31050312"
    },
    "parent": {
      "id": "310503",
      "level": 3,
      "name": {
        "th": "เมืองไผ่",
        "en": "Mueang Phai",
        "slug": "mueang-phai"
      }
    },
    "ancestors": [
      {
        "id": "31",
        "level": 1,
        "name": {
          "th": "บุรีรัมย์",
          "en": "Buri Ram",
          "slug": "buri-ram"
        }
      },
      {
        "id": "3105",
        "level": 2,
        "name": {
          "th": "หนองกี่",
          "en": "Nong Ki",
          "slug": "nong-ki"
        }
      },
      {
        "id": "310503",
        "level": 3,
        "name": {
          "th": "เมืองไผ่",
          "en": "Mueang Phai",
          "slug": "mueang-phai"
        }
      }
    ],
    "children_count": {},
    "metadata": {},
    "geo": {
      "lat": "14.772434207460703",
      "lon": "102.59202852845192"
    },
    "source": {}
  },
  {
    "id": "31050313",
    "level": 4,
    "level_name": {
      "th": "หมู่บ้าน",
      "en": "village"
    },
    "name": {
      "th": "บ้านโนนรัง",
      "en": "Ban Non Rang",
      "slug": "31050313"
    },
    "code": {
      "dopa": "31050313"
    },
    "parent": {
      "id": "310503",
      "level": 3,
      "name": {
        "th": "เมืองไผ่",
        "en": "Mueang Phai",
        "slug": "mueang-phai"
      }
    },
    "ancestors": [
      {
        "id": "31",
        "level": 1,
        "name": {
          "th": "บุรีรัมย์",
          "en": "Buri Ram",
          "slug": "buri-ram"
        }
      },
      {
        "id": "3105",
        "level": 2,
        "name": {
          "th": "หนองกี่",
          "en": "Nong Ki",
          "slug": "nong-ki"
        }
      },
      {
        "id": "310503",
        "level": 3,
        "name": {
          "th": "เมืองไผ่",
          "en": "Mueang Phai",
          "slug": "mueang-phai"
        }
      }
    ],
    "children_count": {},
    "metadata": {},
    "geo": {
      "lat": "14.748275227415956",
      "lon": "102.60704755783081"
    },
    "source": {}
  },
  {
    "id": "31050314",
    "level": 4,
    "level_name": {
      "th": "หมู่บ้าน",
      "en": "village"
    },
    "name": {
      "th": "บ้านหนองไผ่ล้อม",
      "en": "Ban Nong Phai Lom",
      "slug": "31050314"
    },
    "code": {
      "dopa": "31050314"
    },
    "parent": {
      "id": "310503",
      "level": 3,
      "name": {
        "th": "เมืองไผ่",
        "en": "Mueang Phai",
        "slug": "mueang-phai"
      }
    },
    "ancestors": [
      {
        "id": "31",
        "level": 1,
        "name": {
          "th": "บุรีรัมย์",
          "en": "Buri Ram",
          "slug": "buri-ram"
        }
      },
      {
        "id": "3105",
        "level": 2,
        "name": {
          "th": "หนองกี่",
          "en": "Nong Ki",
          "slug": "nong-ki"
        }
      },
      {
        "id": "310503",
        "level": 3,
        "name": {
          "th": "เมืองไผ่",
          "en": "Mueang Phai",
          "slug": "mueang-phai"
        }
      }
    ],
    "children_count": {},
    "metadata": {},
    "geo": {
      "lat": "14.758393561577174",
      "lon": "102.65969395637512"
    },
    "source": {}
  },
  {
    "id": "31050315",
    "level": 4,
    "level_name": {
      "th": "หมู่บ้าน",
      "en": "village"
    },
    "name": {
      "th": "บ้านหนองพันธ์ชุลี",
      "en": "Ban Nong Phan Chuli",
      "slug": "31050315"
    },
    "code": {
      "dopa": "31050315"
    },
    "parent": {
      "id": "310503",
      "level": 3,
      "name": {
        "th": "เมืองไผ่",
        "en": "Mueang Phai",
        "slug": "mueang-phai"
      }
    },
    "ancestors": [
      {
        "id": "31",
        "level": 1,
        "name": {
          "th": "บุรีรัมย์",
          "en": "Buri Ram",
          "slug": "buri-ram"
        }
      },
      {
        "id": "3105",
        "level": 2,
        "name": {
          "th": "หนองกี่",
          "en": "Nong Ki",
          "slug": "nong-ki"
        }
      },
      {
        "id": "310503",
        "level": 3,
        "name": {
          "th": "เมืองไผ่",
          "en": "Mueang Phai",
          "slug": "mueang-phai"
        }
      }
    ],
    "children_count": {},
    "metadata": {},
    "geo": {
      "lat": "14.787490550272073",
      "lon": "102.64664500951767"
    },
    "source": {}
  },
  {
    "id": "31050316",
    "level": 4,
    "level_name": {
      "th": "หมู่บ้าน",
      "en": "village"
    },
    "name": {
      "th": "บ้านน้อยหนองแก",
      "en": "Ban Noi Nong Kae",
      "slug": "31050316"
    },
    "code": {
      "dopa": "31050316"
    },
    "parent": {
      "id": "310503",
      "level": 3,
      "name": {
        "th": "เมืองไผ่",
        "en": "Mueang Phai",
        "slug": "mueang-phai"
      }
    },
    "ancestors": [
      {
        "id": "31",
        "level": 1,
        "name": {
          "th": "บุรีรัมย์",
          "en": "Buri Ram",
          "slug": "buri-ram"
        }
      },
      {
        "id": "3105",
        "level": 2,
        "name": {
          "th": "หนองกี่",
          "en": "Nong Ki",
          "slug": "nong-ki"
        }
      },
      {
        "id": "310503",
        "level": 3,
        "name": {
          "th": "เมืองไผ่",
          "en": "Mueang Phai",
          "slug": "mueang-phai"
        }
      }
    ],
    "children_count": {},
    "metadata": {},
    "geo": {
      "lat": "14.780130435942755",
      "lon": "102.6905407011509"
    },
    "source": {}
  },
  {
    "id": "31050317",
    "level": 4,
    "level_name": {
      "th": "หมู่บ้าน",
      "en": "village"
    },
    "name": {
      "th": "บ้านโนนจันทา",
      "en": "Ban Non Chantha",
      "slug": "31050317"
    },
    "code": {
      "dopa": "31050317"
    },
    "parent": {
      "id": "310503",
      "level": 3,
      "name": {
        "th": "เมืองไผ่",
        "en": "Mueang Phai",
        "slug": "mueang-phai"
      }
    },
    "ancestors": [
      {
        "id": "31",
        "level": 1,
        "name": {
          "th": "บุรีรัมย์",
          "en": "Buri Ram",
          "slug": "buri-ram"
        }
      },
      {
        "id": "3105",
        "level": 2,
        "name": {
          "th": "หนองกี่",
          "en": "Nong Ki",
          "slug": "nong-ki"
        }
      },
      {
        "id": "310503",
        "level": 3,
        "name": {
          "th": "เมืองไผ่",
          "en": "Mueang Phai",
          "slug": "mueang-phai"
        }
      }
    ],
    "children_count": {},
    "metadata": {},
    "geo": {
      "lat": "14.769747271237145",
      "lon": "102.58434802593777"
    },
    "source": {}
  },
  {
    "id": "31050318",
    "level": 4,
    "level_name": {
      "th": "หมู่บ้าน",
      "en": "village"
    },
    "name": {
      "th": "บ้านขามใหญ่",
      "en": "Ban Kham Yai",
      "slug": "31050318"
    },
    "code": {
      "dopa": "31050318"
    },
    "parent": {
      "id": "310503",
      "level": 3,
      "name": {
        "th": "เมืองไผ่",
        "en": "Mueang Phai",
        "slug": "mueang-phai"
      }
    },
    "ancestors": [
      {
        "id": "31",
        "level": 1,
        "name": {
          "th": "บุรีรัมย์",
          "en": "Buri Ram",
          "slug": "buri-ram"
        }
      },
      {
        "id": "3105",
        "level": 2,
        "name": {
          "th": "หนองกี่",
          "en": "Nong Ki",
          "slug": "nong-ki"
        }
      },
      {
        "id": "310503",
        "level": 3,
        "name": {
          "th": "เมืองไผ่",
          "en": "Mueang Phai",
          "slug": "mueang-phai"
        }
      }
    ],
    "children_count": {},
    "metadata": {},
    "geo": {
      "lat": "14.770691",
      "lon": "102.587653"
    },
    "source": {}
  }
]